pulselab/__init__.py
pulselab/pulse.py
pulselab/pulse_lab.py
pulselab/pulses.py
pulselab-1.2.0.dist-info/METADATA
pulselab-1.2.0.dist-info/WHEEL
pulselab-1.2.0.dist-info/RECORD
